notifire/__init__.py
notifire/cli.py
notifire/client.py
notifire/constants.py
notifire/dsn.py
notifire/exceptions.py
notifire/message.py
notifire/integrations/__init__.py
notifire/integrations/raven.py
notifire/transport/__init__.py
notifire/transport/aiohttp.py
notifire/transport/base.py
notifire/transport/gevent.py
notifire/transport/http.py
notifire/transport/requests.py
notifire/transport/threaded.py
notifire/transport/threaded_requests.py
notifire/utils/__init__.py
notifire/utils/compat.py
notifire/utils/http.py
notifire/utils/ssl_match_hostname.py
notifire-0.1.2.dist-info/LICENSE
notifire-0.1.2.dist-info/METADATA
notifire-0.1.2.dist-info/WHEEL
notifire-0.1.2.dist-info/entry_points.txt
notifire-0.1.2.dist-info/top_level.txt
notifire-0.1.2.dist-info/RECORD
