Metadata-Version: 2.1
Name: notifire
Version: 0.1.2
Summary: Python client for Notifire (https://notifire.dvdblk.com)
Home-page: https://github.com/Notifire/notifire-python
Author: Notifire team
Author-email: notifire@memonil.com
License: BSD
Platform: UNKNOWN
Classifier: Intended Audience :: Developers
Classifier: Development Status :: 4 - Beta
Classifier: Environment :: Web Environment
Classifier: Operating System :: OS Independent
Classifier: Programming Language :: Python
Classifier: Programming Language :: Python :: 3
Classifier: Programming Language :: Python :: 3.6
Classifier: Programming Language :: Python :: 3.7
Classifier: Programming Language :: Python :: 3.8
Classifier: Programming Language :: Python :: 3.9
Classifier: Topic :: Software Development :: Libraries :: Python Modules
Requires-Dist: certifi
Provides-Extra: raven
Requires-Dist: raven ; extra == 'raven'
